data_serialize/__init__.py
data_serialize/demo.py
data_serialize/setup.py
data_serialize/pb/__init__.py
data_serialize/pb/example_pb2.py
data_serialize/pb/feature_pb2.py
data_serialize/pb/numpyobject_pb2.py
data_serialize/pb4/__init__.py
data_serialize/pb4/example_pb2.py
data_serialize/pb4/feature_pb2.py
data_serialize/pb4/numpyobject_pb2.py
data_serialize/pb5/__init__.py
data_serialize/pb5/example_pb2.py
data_serialize/pb5/feature_pb2.py
data_serialize/pb5/numpyobject_pb2.py
data_serialize/pb6/__init__.py
data_serialize/pb6/example_pb2.py
data_serialize/pb6/feature_pb2.py
data_serialize/pb6/numpyobject_pb2.py
data_serialize-0.4.1.dist-info/METADATA
data_serialize-0.4.1.dist-info/WHEEL
data_serialize-0.4.1.dist-info/top_level.txt
data_serialize-0.4.1.dist-info/RECORD
