Metadata-Version: 2.1
Name: data-serialize
Version: 0.4.1
Summary: data serialize
Home-page: https://github.com/ssbuild/fastdatasets
Author: ssbuild
Author-email: 9727464@qq.com
License: MIT
Keywords: data_serialize,serialize,deserialize
Platform: UNKNOWN
Requires-Dist: protobuf
